{
  "name": "Kairos",
  "build": {
    "dockerfile": "Dockerfile",
    "context": ".."
  },
  "features": {
    "ghcr.io/devcontainers/features/rust:1": {
      "version": "1.94.1",
      "profile": "default"
    },
    "ghcr.io/devcontainers/features/common-utils:2": {
      "installZsh": true,
      "configureZshAsDefaultShell": true
    }
  },
  "customizations": {
    "vscode": {
      "extensions": [
        "rust-lang.rust-analyzer",
        "vadimcn.vscode-lldb",
        "tamasfe.even-better-toml",
        "ms-vscode.cpptools",
        "ms-vscode.cmake-tools",
        "xmonader.vscode-capnp"
      ],
      "settings": {
        "rust-analyzer.check.command": "clippy"
      }
    }
  },
  "forwardPorts": [],
  "postCreateCommand": "bash .devcontainer/post-create.sh",
  "remoteUser": "vscode"
}
